apath/__init__.py
apath/apath.py
apath-0.5.dist-info/METADATA
apath-0.5.dist-info/WHEEL
apath-0.5.dist-info/top_level.txt
apath-0.5.dist-info/RECORD
